alo_agent_sdk/__init__.py
alo_agent_sdk/alo_a2a/__init__.py
alo_agent_sdk/alo_a2a/cli.py
alo_agent_sdk/alo_a2a/client.py
alo_agent_sdk/alo_a2a/exceptions.py
alo_agent_sdk/alo_a2a/agent_flow/__init__.py
alo_agent_sdk/alo_a2a/agent_flow/cli.py
alo_agent_sdk/alo_a2a/agent_flow/engine/__init__.py
alo_agent_sdk/alo_a2a/agent_flow/engine/executor.py
alo_agent_sdk/alo_a2a/agent_flow/examples/__init__.py
alo_agent_sdk/alo_a2a/agent_flow/models/__init__.py
alo_agent_sdk/alo_a2a/agent_flow/models/agent.py
alo_agent_sdk/alo_a2a/agent_flow/models/tool.py
alo_agent_sdk/alo_a2a/agent_flow/models/workflow.py
alo_agent_sdk/alo_a2a/agent_flow/server/__init__.py
alo_agent_sdk/alo_a2a/agent_flow/server/agent_api.py
alo_agent_sdk/alo_a2a/agent_flow/server/api.py
alo_agent_sdk/alo_a2a/agent_flow/server/web.py
alo_agent_sdk/alo_a2a/agent_flow/server/static/__init__.py
alo_agent_sdk/alo_a2a/agent_flow/storage/__init__.py
alo_agent_sdk/alo_a2a/agent_flow/storage/workflow_storage.py
alo_agent_sdk/alo_a2a/agent_flow/utils/agent_manager.py
alo_agent_sdk/alo_a2a/client/__init__.py
alo_agent_sdk/alo_a2a/client/base.py
alo_agent_sdk/alo_a2a/client/http.py
alo_agent_sdk/alo_a2a/client/network.py
alo_agent_sdk/alo_a2a/client/router.py
alo_agent_sdk/alo_a2a/client/streaming.py
alo_agent_sdk/alo_a2a/client/llm/__init__.py
alo_agent_sdk/alo_a2a/client/llm/anthropic.py
alo_agent_sdk/alo_a2a/client/llm/bedrock.py
alo_agent_sdk/alo_a2a/client/llm/openai.py
alo_agent_sdk/alo_a2a/core/__init__.py
alo_agent_sdk/alo_a2a/core/prompts.py
alo_agent_sdk/alo_a2a/discovery/__init__.py
alo_agent_sdk/alo_a2a/discovery/client.py
alo_agent_sdk/alo_a2a/discovery/registry.py
alo_agent_sdk/alo_a2a/discovery/server.py
alo_agent_sdk/alo_a2a/docs/__init__.py
alo_agent_sdk/alo_a2a/docs/openai.py
alo_agent_sdk/alo_a2a/mcp/__init__.py
alo_agent_sdk/alo_a2a/mcp/agent.py
alo_agent_sdk/alo_a2a/mcp/client.py
alo_agent_sdk/alo_a2a/mcp/config_models.py
alo_agent_sdk/alo_a2a/mcp/exceptions.py
alo_agent_sdk/alo_a2a/mcp/fastmcp.py
alo_agent_sdk-0.3.2.dist-info/METADATA
alo_agent_sdk-0.3.2.dist-info/WHEEL
alo_agent_sdk-0.3.2.dist-info/entry_points.txt
alo_agent_sdk-0.3.2.dist-info/top_level.txt
alo_agent_sdk-0.3.2.dist-info/RECORD
