Metadata-Version: 2.4
Name: alo-agent-sdk
Version: 0.3.2
Summary: SDK for building and deploying AI agents, with project templating.
Author-email: Daniele Ligorio / Alomana <dl@alomana.com>
License: MIT
Project-URL: Homepage, https://github.com/aidataspark/alo-agent-sdk
Project-URL: Repository, https://github.com/aidataspark/alo-agent-sdk
Project-URL: Bug Tracker, https://github.com/aidataspark/alo-agent-sdk/issues
Classifier: Development Status :: 3 - Alpha
Classifier: Intended Audience :: Developers
Classifier: Programming Language :: Python :: 3
Classifier: Programming Language :: Python :: 3.8
Classifier: Programming Language :: Python :: 3.9
Classifier: Programming Language :: Python :: 3.10
Classifier: Programming Language :: Python :: 3.11
Classifier: License :: OSI Approved :: MIT License
Classifier: Operating System :: OS Independent
Classifier: Topic :: Software Development :: Libraries :: Application Frameworks
Requires-Python: >=3.8
Requires-Dist: fastapi==0.110.3
Requires-Dist: uvicorn[standard]==0.24.0.post1
Requires-Dist: httpx==0.28.1
Requires-Dist: pydantic==2.11.3
Requires-Dist: requests==2.32.3
Requires-Dist: typer==0.16.0
Requires-Dist: jinja2==3.1.6
Requires-Dist: python-dotenv<2.0.0,>=0.21.0
Requires-Dist: ruamel.yaml<0.19.0,>=0.17.21
Requires-Dist: pydantic-ai==0.2.18
Requires-Dist: openai==1.86.0
Provides-Extra: openai
Requires-Dist: openai<2.0.0,>=1.0.0; extra == "openai"
Provides-Extra: anthropic
Requires-Dist: anthropic<1.0.0,>=0.20.0; extra == "anthropic"
Provides-Extra: bedrock
Requires-Dist: boto3<2.0.0,>=1.20.0; extra == "bedrock"
Requires-Dist: aioboto3<13.0.0,>=10.0.0; extra == "bedrock"
Provides-Extra: all
Requires-Dist: openai<2.0.0,>=1.0.0; extra == "all"
Requires-Dist: anthropic<1.0.0,>=0.20.0; extra == "all"
Requires-Dist: boto3<2.0.0,>=1.20.0; extra == "all"
Requires-Dist: aioboto3<13.0.0,>=10.0.0; extra == "all"
